Flask_AppBuilder_hack-1.12.5.dist-info/DESCRIPTION.rst
Flask_AppBuilder_hack-1.12.5.dist-info/METADATA
Flask_AppBuilder_hack-1.12.5.dist-info/RECORD
Flask_AppBuilder_hack-1.12.5.dist-info/WHEEL
Flask_AppBuilder_hack-1.12.5.dist-info/entry_points.txt
Flask_AppBuilder_hack-1.12.5.dist-info/metadata.json
Flask_AppBuilder_hack-1.12.5.dist-info/top_level.txt
flask_appbuilder/__init__.py
flask_appbuilder/_compat.py
flask_appbuilder/actions.py
flask_appbuilder/base.py
flask_appbuilder/baseapp.py
flask_appbuilder/basemanager.py
flask_appbuilder/baseviews.py
flask_appbuilder/console.py
flask_appbuilder/const.py
flask_appbuilder/fields.py
flask_appbuilder/fieldwidgets.py
flask_appbuilder/filemanager.py
flask_appbuilder/filters.py
flask_appbuilder/forms.py
flask_appbuilder/menu.py
flask_appbuilder/messages.py
flask_appbuilder/upload.py
flask_appbuilder/urltools.py
flask_appbuilder/validators.py
flask_appbuilder/version.py
flask_appbuilder/views.py
flask_appbuilder/widgets.py
flask_appbuilder/babel/__init__.py
flask_appbuilder/babel/manager.py
flask_appbuilder/babel/views.py
flask_appbuilder/charts/__init__.py
flask_appbuilder/charts/jsontools.py
flask_appbuilder/charts/views.py
flask_appbuilder/charts/widgets.py
flask_appbuilder/models/__init__.py
flask_appbuilder/models/base.py
flask_appbuilder/models/datamodel.py
flask_appbuilder/models/decorators.py
flask_appbuilder/models/filters.py
flask_appbuilder/models/group.py
flask_appbuilder/models/mixins.py
flask_appbuilder/models/generic/__init__.py
flask_appbuilder/models/generic/filters.py
flask_appbuilder/models/generic/interface.py
flask_appbuilder/models/mongoengine/__init__.py
flask_appbuilder/models/mongoengine/fields.py
flask_appbuilder/models/mongoengine/filters.py
flask_appbuilder/models/mongoengine/interface.py
flask_appbuilder/models/sqla/__init__.py
flask_appbuilder/models/sqla/filters.py
flask_appbuilder/models/sqla/interface.py
flask_appbuilder/security/__init__.py
flask_appbuilder/security/decorators.py
flask_appbuilder/security/forms.py
flask_appbuilder/security/manager.py
flask_appbuilder/security/registerviews.py
flask_appbuilder/security/views.py
flask_appbuilder/security/mongoengine/__init__.py
flask_appbuilder/security/mongoengine/manager.py
flask_appbuilder/security/mongoengine/models.py
