Metadata-Version: 2.0
Name: Flask-AppBuilder-hack
Version: 1.12.5
Summary: Simple and rapid application development framework, built on top of Flask. includes detailed security, auto CRUD generation for your models, google charts and much more.
Home-page: https://github.com/sunliwen/lask-appbuilder/
Author: Daniel Vaz Gaspar
Author-email: danielvazgaspar@gmail.com
License: BSD
Platform: any
Classifier: Development Status :: 5 - Production/Stable
Classifier: Environment :: Web Environment
Classifier: Intended Audience :: Developers
Classifier: License :: OSI Approved :: BSD License
Classifier: Operating System :: OS Independent
Classifier: Programming Language :: Python
Classifier: Topic :: Software Development :: Libraries :: Python Modules
Requires-Dist: Flask-Babel (<1,>=0.11.1)
Requires-Dist: Flask-Login (<0.5,>=0.3)
Requires-Dist: Flask-OpenID (<2,>=1.2.5)
Requires-Dist: Flask-SQLAlchemy (<3,>=2.3)
Requires-Dist: Flask-WTF (<1,>=0.14.2)
Requires-Dist: Flask (<2,>=0.12)
Requires-Dist: PyJWT (>=1.7.1)
Requires-Dist: click (<8,>=6.7)
Requires-Dist: colorama (<1,>=0.3.9)
Requires-Dist: python-dateutil (<3,>=2.3)
